pygha/__init__.py
pygha/__main__.py
pygha/cli.py
pygha/decorators.py
pygha/expr.py
pygha/models.py
pygha/registry.py
pygha/trigger_event.py
pygha/steps/__init__.py
pygha/steps/api.py
pygha/steps/builtin.py
pygha/transpilers/github.py
pygha-0.3.1.dist-info/METADATA
pygha-0.3.1.dist-info/WHEEL
pygha-0.3.1.dist-info/entry_points.txt
pygha-0.3.1.dist-info/licenses/LICENSE
pygha-0.3.1.dist-info/RECORD
