Metadata-Version: 2.4
Name: pygha
Version: 0.3.1
Summary: A Python-native CI/CD framework for defining, testing, and transpiling pipelines.
License: MIT
License-File: LICENSE
Classifier: License :: OSI Approved :: MIT License
Classifier: Operating System :: OS Independent
Classifier: Programming Language :: Python :: 3
Classifier: Programming Language :: Python :: 3.11
Classifier: Programming Language :: Python :: 3.12
Classifier: Programming Language :: Python :: 3.13
Classifier: Programming Language :: Python :: 3.14
Requires-Python: >=3.11
Requires-Dist: ruamel-yaml>=0.18.0
Provides-Extra: dev
Requires-Dist: bandit>=1.7; extra == 'dev'
Requires-Dist: build; extra == 'dev'
Requires-Dist: mypy>=1.11; extra == 'dev'
Requires-Dist: pytest-cov>=5.0; extra == 'dev'
Requires-Dist: pytest>=8.0; extra == 'dev'
Requires-Dist: ruff>=0.6; extra == 'dev'
Requires-Dist: tox>=4.18; extra == 'dev'
Requires-Dist: twine; extra == 'dev'
Provides-Extra: docs
Requires-Dist: sphinx-autodoc-typehints>=2.4.4; extra == 'docs'
Requires-Dist: sphinx>=8.0.2; extra == 'docs'
